hiscovid.py
hiscovid-0.0.5.dist-info/METADATA
hiscovid-0.0.5.dist-info/WHEEL
hiscovid-0.0.5.dist-info/entry_points.txt
hiscovid-0.0.5.dist-info/top_level.txt
hiscovid-0.0.5.dist-info/RECORD
