Metadata-Version: 2.1
Name: hiscovid
Version: 0.0.5
Summary: A package for calculating time transition policy scores against COVID-19
Home-page: https://github.com/y-takefuji/hiscovid
Author: yoshiyasu takefuji
Author-email: takefuji@keio.jp
License: UNKNOWN
Project-URL: Bug Tracker, https://github.com/y-takefuji/hiscovid
Platform: UNKNOWN
Classifier: Programming Language :: Python :: 3
Classifier: License :: OSI Approved :: MIT License
Classifier: Operating System :: OS Independent
Requires-Python: >=3.8
